vgis_utils/__init__.py
vgis_utils/commonTools.py
vgis_utils/iteratorTools.py
vgis_utils/vgis_card/__init__.py
vgis_utils/vgis_card/cardTools.py
vgis_utils/vgis_datetime/__init__.py
vgis_utils/vgis_datetime/datetimeTools.py
vgis_utils/vgis_file/__init__.py
vgis_utils/vgis_file/fileTools.py
vgis_utils/vgis_http/__init__.py
vgis_utils/vgis_http/httpTools.py
vgis_utils/vgis_image/__init__.py
vgis_utils/vgis_image/imageTools.py
vgis_utils/vgis_list/__init__.py
vgis_utils/vgis_list/listTools.py
vgis_utils/vgis_math/__init__.py
vgis_utils/vgis_math/mathTools.py
vgis_utils/vgis_money/__init__.py
vgis_utils/vgis_money/moneyTools.py
vgis_utils/vgis_number/__init__.py
vgis_utils/vgis_number/numberTools.py
vgis_utils/vgis_string/__init__.py
vgis_utils/vgis_string/stringTools.py
vgis_utils/vgis_video/__init__.py
vgis_utils/vgis_video/videoTools.py
vgis_utils/vgis_zip/__init__.py
vgis_utils/vgis_zip/zipTools.py
vgis_utils-1.4.5.dist-info/METADATA
vgis_utils-1.4.5.dist-info/WHEEL
vgis_utils-1.4.5.dist-info/top_level.txt
vgis_utils-1.4.5.dist-info/RECORD
